brunette/__init__.py
brunette/__main__.py
brunette/brunette.py
brunette-0.2.8.dist-info/METADATA
brunette-0.2.8.dist-info/WHEEL
brunette-0.2.8.dist-info/entry_points.txt
brunette-0.2.8.dist-info/top_level.txt
brunette-0.2.8.dist-info/RECORD
