Metadata-Version: 2.1
Name: brunette
Version: 0.2.8
Summary: A best practice Python code formatter
Home-page: https://github.com/ODwyerSoftware/brunette
Author: O'Dwyer Software
Author-email: hello@odwyer.software
License: Apache 2.0
Platform: UNKNOWN
Classifier: Intended Audience :: Developers
Classifier: Operating System :: OS Independent
Classifier: Programming Language :: Python
Classifier: Programming Language :: Python :: 3
Classifier: Topic :: Internet :: WWW/HTTP
Requires-Dist: setuptools
Requires-Dist: wheel
Requires-Dist: black (==21.12b0)
Requires-Dist: click
Provides-Extra: dev
Requires-Dist: pytest (==5.4.1) ; extra == 'dev'
Requires-Dist: coverage (==5.1) ; extra == 'dev'
Requires-Dist: flake8 (==3.8.0a2) ; extra == 'dev'
Requires-Dist: pep8-naming (==0.10.0) ; extra == 'dev'
Requires-Dist: pytest-cov (==2.8.1) ; extra == 'dev'
Requires-Dist: mccabe (==0.6.1) ; extra == 'dev'
Requires-Dist: zest.releaser (==6.20.1) ; extra == 'dev'
Requires-Dist: ipdb (==0.13.2) ; extra == 'dev'
Requires-Dist: tox (==3.15.0) ; extra == 'dev'
